basicco/__init__.py
basicco/_bases.py
basicco/abstract_class.py
basicco/caller_module.py
basicco/context_vars.py
basicco/custom_repr.py
basicco/default_dir.py
basicco/descriptors.py
basicco/dynamic_class.py
basicco/dynamic_code.py
basicco/explicit_hash.py
basicco/fabricate_value.py
basicco/func_tools.py
basicco/get_mro.py
basicco/hash_cache_wrapper.py
basicco/implicit_hash.py
basicco/import_path.py
basicco/init_subclass.py
basicco/lazy_tuple.py
basicco/locked_class.py
basicco/mangling.py
basicco/mapping_proxy.py
basicco/namespace.py
basicco/null_context.py
basicco/obj_state.py
basicco/py.typed
basicco/qualname.py
basicco/recursive_repr.py
basicco/runtime_final.py
basicco/safe_not_equals.py
basicco/safe_repr.py
basicco/sentinel.py
basicco/set_name.py
basicco/suppress_exception.py
basicco/type_checking.py
basicco/unique_iterator.py
basicco-10.5.8.dist-info/LICENSE
basicco-10.5.8.dist-info/METADATA
basicco-10.5.8.dist-info/WHEEL
basicco-10.5.8.dist-info/top_level.txt
basicco-10.5.8.dist-info/RECORD
