Metadata-Version: 2.1
Name: basicco
Version: 10.5.8
Summary: Bases and utilities for compatibility, features and validation.
Home-page: https://github.com/brunonicko/basicco
Author: Bruno Nicko
Author-email: brunonicko@gmail.com
Classifier: Intended Audience :: Developers
Classifier: License :: OSI Approved :: MIT License
Classifier: Operating System :: OS Independent
Classifier: Programming Language :: Python :: 2.7
Classifier: Programming Language :: Python :: 3.7
Classifier: Programming Language :: Python :: 3.8
Classifier: Programming Language :: Python :: 3.9
Classifier: Programming Language :: Python :: 3.10
Classifier: Programming Language :: Python :: 3.11
Classifier: Programming Language :: Python :: 3.12
Classifier: Programming Language :: Python :: Implementation :: PyPy
Requires-Python: >= 2.7, != 3.0.*, != 3.1.*, != 3.2.*, != 3.3.*, != 3.4.*, != 3.5.*, != 3.6.*
License-File: LICENSE
Requires-Dist: six
Requires-Dist: slotted <6,>=5.1
Requires-Dist: tippo <5,>=4
Requires-Dist: typing-inspect <1,>=0
Requires-Dist: enum34 ; python_version < "3.4"
